blender_asset_tracer/__init__.py
blender_asset_tracer/blendfile/__init__.py
blender_asset_tracer/blendfile/dna.py
blender_asset_tracer/blendfile/dna_io.py
blender_asset_tracer/blendfile/exceptions.py
blender_asset_tracer/blendfile/header.py
blender_asset_tracer/blendfile/iterators.py
blender_asset_tracer/blendfile/magic_compression.py
blender_asset_tracer/bpathlib.py
blender_asset_tracer/cdefs.py
blender_asset_tracer/cli/__init__.py
blender_asset_tracer/cli/blocks.py
blender_asset_tracer/cli/common.py
blender_asset_tracer/cli/list_deps.py
blender_asset_tracer/cli/pack.py
blender_asset_tracer/cli/version.py
blender_asset_tracer/compressor.py
blender_asset_tracer/pack/__init__.py
blender_asset_tracer/pack/filesystem.py
blender_asset_tracer/pack/progress.py
blender_asset_tracer/pack/s3.py
blender_asset_tracer/pack/shaman/__init__.py
blender_asset_tracer/pack/shaman/cache.py
blender_asset_tracer/pack/shaman/client.py
blender_asset_tracer/pack/shaman/time_tracker.py
blender_asset_tracer/pack/shaman/transfer.py
blender_asset_tracer/pack/transfer.py
blender_asset_tracer/pack/zipped.py
blender_asset_tracer/trace/__init__.py
blender_asset_tracer/trace/blocks2assets.py
blender_asset_tracer/trace/expanders.py
blender_asset_tracer/trace/file2blocks.py
blender_asset_tracer/trace/file_sequence.py
blender_asset_tracer/trace/modifier_walkers.py
blender_asset_tracer/trace/progress.py
blender_asset_tracer/trace/result.py
blender_asset_tracer-1.19.dist-info/LICENSE.txt
blender_asset_tracer-1.19.dist-info/METADATA
blender_asset_tracer-1.19.dist-info/WHEEL
blender_asset_tracer-1.19.dist-info/entry_points.txt
blender_asset_tracer-1.19.dist-info/RECORD
