Metadata-Version: 2.3
Name: blender-asset-tracer
Version: 1.19
Summary: BAT parses Blend files and produces dependency information. After installation run `bat --help`
License: GPL-2.0+
Author: Sybren A. Stüvel
Author-email: sybren@blender.org
Requires-Python: >=3.9,<4.0
Classifier: Environment :: Console
Classifier: Intended Audience :: Developers
Classifier: License :: OSI Approved :: GNU General Public License v2 or later (GPLv2+)
Classifier: Operating System :: OS Independent
Classifier: Programming Language :: Python :: 3
Classifier: Programming Language :: Python :: 3.9
Classifier: Programming Language :: Python :: 3.10
Classifier: Programming Language :: Python :: 3.11
Classifier: Programming Language :: Python :: 3.12
Classifier: Programming Language :: Python :: 3.13
Classifier: Topic :: Utilities
Provides-Extra: s3
Provides-Extra: zstandard
Requires-Dist: boto3 (>=1.9,<2.0) ; extra == "s3"
Requires-Dist: requests (>=2.11,<3.0)
Requires-Dist: zstandard (>=0.15,<0.16) ; extra == "zstandard"
Project-URL: Homepage, https://developer.blender.org/project/profile/79/
